torchattack/__init__.py
torchattack/_rgetattr.py
torchattack/admix.py
torchattack/att.py
torchattack/attack.py
torchattack/attack_model.py
torchattack/bfa.py
torchattack/bia.py
torchattack/bpa.py
torchattack/bsr.py
torchattack/cda.py
torchattack/create_attack.py
torchattack/danaa.py
torchattack/decowa.py
torchattack/deepfool.py
torchattack/difgsm.py
torchattack/dr.py
torchattack/fda.py
torchattack/fgsm.py
torchattack/fia.py
torchattack/gama.py
torchattack/geoda.py
torchattack/gra.py
torchattack/ilpd.py
torchattack/l2t.py
torchattack/ltp.py
torchattack/mifgsm.py
torchattack/mig.py
torchattack/mumodig.py
torchattack/naa.py
torchattack/nifgsm.py
torchattack/pgd.py
torchattack/pgdl2.py
torchattack/pna_patchout.py
torchattack/py.typed
torchattack/sgm.py
torchattack/sinifgsm.py
torchattack/ssa.py
torchattack/ssp.py
torchattack/tgr.py
torchattack/tifgsm.py
torchattack/vdc.py
torchattack/vmifgsm.py
torchattack/vnifgsm.py
torchattack/evaluate/__init__.py
torchattack/evaluate/dataset.py
torchattack/evaluate/meter.py
torchattack/evaluate/runner.py
torchattack/evaluate/save_image.py
torchattack/generative/__init__.py
torchattack/generative/_weights.py
torchattack/generative/leaky_relu_resnet_generator.py
torchattack/generative/resnet_generator.py
torchattack-1.7.2.dist-info/licenses/LICENSE
torchattack-1.7.2.dist-info/METADATA
torchattack-1.7.2.dist-info/WHEEL
torchattack-1.7.2.dist-info/top_level.txt
torchattack-1.7.2.dist-info/RECORD
