Metadata-Version: 2.4
Name: torchattack
Version: 1.7.2
Summary: A curated list of adversarial attacks in PyTorch, with a focus on transferable black-box attacks
Author-email: spencerwooo <spencer.woo@outlook.com>
License: MIT License
Project-URL: Repository, https://github.com/spencerwooo/torchattack
Project-URL: Documentation, https://github.com/spencerwooo/torchattack/blob/main/README.md
Classifier: Development Status :: 5 - Production/Stable
Classifier: Environment :: GPU :: NVIDIA CUDA
Classifier: Intended Audience :: Developers
Classifier: License :: OSI Approved :: MIT License
Classifier: Operating System :: OS Independent
Classifier: Programming Language :: Python :: 3.10
Classifier: Programming Language :: Python :: 3.11
Classifier: Programming Language :: Python :: 3.12
Classifier: Programming Language :: Python :: 3.13
Classifier: Programming Language :: Python :: 3 :: Only
Classifier: Topic :: Software Development :: Libraries :: Python Modules
Requires-Python: <3.14,>=3.10
License-File: LICENSE
Requires-Dist: torch>=1.13.0
Requires-Dist: torchvision>=0.14.0
Requires-Dist: numpy>=1.24.2
Provides-Extra: kornia
Requires-Dist: kornia>=0.8.1; extra == "kornia"
Provides-Extra: scipy
Requires-Dist: scipy>=1.15.3; extra == "scipy"
Dynamic: license-file
